[{"pk":"10E348E2-ECED-D646-9579-CF9B1CE3882B","solicitud":15,"granalla":"XYZ - GLATTEN 40","cantidad":1000,"fecha":"12\/06\/2023 11:20:30","usuario":"ios","cliente":"GUNDERSON CONCARRIL","status":"Entregada"},{"pk":"21811B9D-ADFC-5141-A535-3CCD1F10C6D0","solicitud":14,"granalla":"Airkantisch-mix","cantidad":3,"fecha":"10\/12\/2023 08:00:08","usuario":"test3","cliente":"GUNDERSON CONCARRIL","status":"Recibida"},{"pk":"1CD4930E-1F0C-CE47-8930-B32400A84A63","solicitud":13,"granalla":"Airkantisch-mix","cantidad":1,"fecha":"10\/12\/2023 07:49:16","usuario":"test3","cliente":"GUNDERSON CONCARRIL","status":"Entregada"},{"pk":"DB71A9C2-6963-F944-BF5C-EE08945C2FA3","solicitud":12,"granalla":"Airkantisch-mix","cantidad":1000,"fecha":"09\/16\/2023 10:00:00","usuario":"test3","cliente":"GUNDERSON CONCARRIL","status":"Entregada"}]